verbatim_llm/__init__.py
verbatim_llm/metrics.py
verbatim_llm/tokenswap.py
verbatim_llm-0.2.0.dist-info/METADATA
verbatim_llm-0.2.0.dist-info/WHEEL
verbatim_llm-0.2.0.dist-info/top_level.txt
verbatim_llm-0.2.0.dist-info/RECORD
